ayikla/__init__.py
ayikla/extractor.py
ayikla/firmalar.txt
ayikla/isimler.txt
ayikla/kurlar.txt
ayikla/lokasyon.txt
ayikla/olculer.txt
ayikla/soyisimler.txt
ayikla-1.2.0.dist-info/METADATA
ayikla-1.2.0.dist-info/WHEEL
ayikla-1.2.0.dist-info/top_level.txt
ayikla-1.2.0.dist-info/RECORD
