Metadata-Version: 2.4
Name: ayikla
Version: 1.2.0
Summary: Türkçe metinlerden isim, telefon, tarih/saat, tarih aralıkları, lokasyon/adres, firma adları, TCKN, IBAN, e-posta, web sitesi, IP adresi, UUID4, miktar/ölçü birimi (olculer) ve para birimi (kurlar) ayıklayan kütüphane.
Author: Çağrı Güngör
License: MIT
Project-URL: Homepage, https://pypi.org/project/ayikla/
Keywords: nlp,turkish,entity-extraction,ayikla,adres,adres-ayiklama,isim-soyisim
Requires-Python: >=3.8
Requires-Dist: phonenumbers
Requires-Dist: python-dateutil
Requires-Dist: dateparser
